unittest_specs/__init__.py
unittest_specs/fun_test_spec.py
unittest_specs/simple_test_spec.py
unittest_specs/test_fun_test_spec_dsl.py
unittest_specs/test_simple_test_spec_dsl.py
unittest_specs/test_with_test_spec.py
unittest_specs/with_test_spec.py
unittest_specs-1.2.0.dist-info/LICENSE
unittest_specs-1.2.0.dist-info/METADATA
unittest_specs-1.2.0.dist-info/WHEEL
unittest_specs-1.2.0.dist-info/top_level.txt
unittest_specs-1.2.0.dist-info/RECORD
