Metadata-Version: 2.1
Name: unittest-specs
Version: 1.2.0
Summary: A simple wrapper around the unittest package with different styles for specs
Home-page: https://github.com/phillipgoellner/unittest_specs
Author: Phillip Goellner
License: BSD Three-Clause License
Project-URL: Source (GitHub), https://github.com/phillipgoellner/unittest_specs
Project-URL: Source (GitLab), https://gitlab.com/goellnerphillip/unittest_specs
Classifier: Development Status :: 4 - Beta
Classifier: Intended Audience :: Developers
Classifier: Programming Language :: Python :: 3
License-File: LICENSE
